pykrx/NanumBarunGothic.ttf
pykrx/__init__.py
pykrx/bond/__init__.py
pykrx/bond/bond.py
pykrx/stock/__init__.py
pykrx/stock/future_api.py
pykrx/stock/stock_api.py
pykrx/website/__init__.py
pykrx/website/comm/__init__.py
pykrx/website/comm/util.py
pykrx/website/comm/webio.py
pykrx/website/krx/__init__.py
pykrx/website/krx/krxio.py
pykrx/website/krx/bond/__init__.py
pykrx/website/krx/bond/core.py
pykrx/website/krx/bond/ticker.py
pykrx/website/krx/bond/wrap.py
pykrx/website/krx/etx/__init__.py
pykrx/website/krx/etx/core.py
pykrx/website/krx/etx/ticker.py
pykrx/website/krx/etx/wrap.py
pykrx/website/krx/future/__init__.py
pykrx/website/krx/future/core.py
pykrx/website/krx/future/wrap.py
pykrx/website/krx/market/__init__.py
pykrx/website/krx/market/core.py
pykrx/website/krx/market/ticker.py
pykrx/website/krx/market/wrap.py
pykrx/website/naver/__init__.py
pykrx/website/naver/core.py
pykrx/website/naver/wrap.py
pykrx-1.0.50.dist-info/METADATA
pykrx-1.0.50.dist-info/WHEEL
pykrx-1.0.50.dist-info/top_level.txt
pykrx-1.0.50.dist-info/RECORD
