Metadata-Version: 2.4
Name: pykrx
Version: 1.0.50
Summary: KRX data scraping
Home-page: https://github.com/liante0904/pykrx
Author: Brayden Jo, Jonghun Yoo
Author-email: brayden.jo@outlook.com, jonghun.yoo@outlook.com, pystock@outlook.com
License: MIT
Requires-Python: >=3
Requires-Dist: requests
Requires-Dist: pandas
Requires-Dist: datetime
Requires-Dist: numpy
Requires-Dist: xlrd
Requires-Dist: deprecated
Requires-Dist: multipledispatch
Requires-Dist: matplotlib
Dynamic: author
Dynamic: author-email
Dynamic: description
Dynamic: description-content-type
Dynamic: home-page
Dynamic: license
Dynamic: requires-dist
Dynamic: requires-python
Dynamic: summary
